gensio_modems/__init__.py
gensio_modems/ax25.py
gensio_modems/gutils.py
gensio_modems/proxy.py
gensio_modems/rmsgw.py
gensio_modems/vara.py
gensio_modems-0.5.0.dist-info/METADATA
gensio_modems-0.5.0.dist-info/WHEEL
gensio_modems-0.5.0.dist-info/top_level.txt
gensio_modems-0.5.0.dist-info/RECORD
