Metadata-Version: 2.1
Name: gensio-modems
Version: 0.5.0
Summary: python-based ham-radio modem utilities (ax25, kiss, vara) built using gensio
Author-email: Masen Furer KF7HVM <kf7hvm@0x26.net>
Project-URL: Homepage, https://github.com/masenf/gensio-modems
Keywords: Ham Radio,KISS,AX.25
Requires-Dist: gensio-binary (>=2.5.5)
